meteocatpy/README.md
meteocatpy/__init__.py
meteocatpy/alerts.py
meteocatpy/const.py
meteocatpy/data.py
meteocatpy/exceptions.py
meteocatpy/forecast.py
meteocatpy/helpers.py
meteocatpy/infostation.py
meteocatpy/lightning.py
meteocatpy/py.typed
meteocatpy/quotes.py
meteocatpy/stations.py
meteocatpy/symbols.py
meteocatpy/town.py
meteocatpy/townstations.py
meteocatpy/uvi.py
meteocatpy/variables.py
meteocatpy/version.py
meteocatpy-1.0.5.dist-info/METADATA
meteocatpy-1.0.5.dist-info/WHEEL
meteocatpy-1.0.5.dist-info/licenses/AUTHORS.md
meteocatpy-1.0.5.dist-info/licenses/LICENSE
meteocatpy-1.0.5.dist-info/RECORD
