Metadata-Version: 2.4
Name: meteocatpy
Version: 1.0.5
Summary: Script para obtener datos meteorológicos de la API de Meteocat
License: Apache-2.0
License-File: AUTHORS.md
License-File: LICENSE
Keywords: meteocatpy,meteocat
Author: figorr
Author-email: jdcuartero@yahoo.es
Requires-Python: >=3.12,<4.0
Classifier: License :: OSI Approved :: Apache Software License
Classifier: Programming Language :: Python :: 3
Classifier: Programming Language :: Python :: 3.12
Classifier: Programming Language :: Python :: 3.13
Classifier: Programming Language :: Python :: 3.14
Requires-Dist: aiofiles (>=24.1.0,<25.0.0)
Requires-Dist: aiohttp (>=3.10.11,<4.0.0) ; python_version < "3.14"
Requires-Dist: aiohttp (>=3.8.0) ; python_version >= "3.14"
Requires-Dist: diskcache (>=5.6.3,<6.0.0)
Requires-Dist: geopy (>=2.4.1,<3.0.0)
Requires-Dist: python-dotenv (>=1.0.1,<2.0.0)
Requires-Dist: python-semantic-release (>=7.28.1,<8.0.0)
Requires-Dist: requests (>=2.32.3,<3.0.0)
Requires-Dist: semantic-release (>=0.1.0,<0.2.0)
Requires-Dist: setuptools (>=75.5.0,<76.0.0)
Requires-Dist: simplejson (>=3.19.3,<4.0.0)
Requires-Dist: twine (>=3,<4)
Requires-Dist: tzdata (>=2024.2,<2025.0)
Requires-Dist: voluptuous (>=0.15.2)
Project-URL: Repository, https://gitlab.com/figorr/meteocatpy
